{"title": "《 蝎 子 赖 赖 》", "stat": {"aid": 1402843337, "view": 461489, "danmaku": 209, "reply": 438, "favorite": 1394, "coin": 354, "share": 795, "now_rank": 0, "his_rank": 0, "like": 59291, "dislike": 0, "vt": 0, "vv": 461489}, "desc": "-", "cid": 1501754210, "hashtag": [{"tag_id": 0, "tag_name": "Celebrate (From the Original Motion Picture \"Penguins of Madagascar\")", "music_id": "MA429660144398302065", "tag_type": "bgm", "jump_url": "https://music.bilibili.com/h5/music-detail?music_id=MA429660144398302065&cid=1501754210&aid=1402843337"}, {"tag_id": 9222, "tag_name": "英雄联盟", "music_id": "", "tag_type": "old_channel", "jump_url": ""}, {"tag_id": 1833, "tag_name": "搞笑", "music_id": "", "tag_type": "old_channel", "jump_url": ""}, {"tag_id": 3093, "tag_name": "LOL", "music_id": "", "tag_type": "old_channel", "jump_url": ""}, {"tag_id": 62526, "tag_name": "电子竞技", "music_id": "", "tag_type": "old_channel", "jump_url": ""}, {"tag_id": 66406, "tag_name": "精彩集锦", "music_id": "", "tag_type": "old_channel", "jump_url": ""}, {"tag_id": 254029, "tag_name": "MOBA", "music_id": "", "tag_type": "old_channel", "jump_url": ""}, {"tag_id": 3217370, "tag_name": "阳光大男孩", "music_id": "", "tag_type": "old_channel", "jump_url": ""}, {"tag_id": 6280278, "tag_name": "觅渡", "music_id": "", "tag_type": "old_channel", "jump_url": ""}, {"tag_id": 17154283, "tag_name": "觅渡Dzg", "music_id": "", "tag_type": "old_channel", "jump_url": ""}], "subtitles": {"allow_submit": false, "lan": "", "lan_doc": "", "subtitles": []}, "comments": [{"content": "蝎子改成这样确实还可以，遇到好几把了，玩的是真开心[笑哭]", "like": 1507}, {"content": "我说这e怎么看着这么眼熟，原来是奎桑提设计师设计的技能", "like": 1908}, {"content": "奥拉夫:这w比我射的都远[笑哭]", "like": 1534}, {"content": "有控制，有位移，能让对面红温，阳光开朗的笑声，是小丑没错了[doge]", "like": 577}, {"content": "很难相信这还是被削了两次才出体验服的强度", "like": 398}, {"content": "这一次十年的数值你挡得住吗？！", "like": 41}, {"content": "这就是蝎子，前面忘了，后面忘了.....啊啊啊啊啊", "like": 136}, {"content": "那皇子w有什么用呢[妙啊]这不被完爆啊", "like": 3}, {"content": "大招是控制，有护盾，有拍地板，没错，他就是。。。", "like": 79}, {"content": "远古之灵·墨菲特[doge]", "like": 59}, {"content": "蝎子走上路能折磨死传统战士，只需要出肉装，开团或者支援保证大招中了就行，E能顶晕对面更好，就是太吃队友", "like": 6}, {"content": "《彗星》《焦灼》《正面能力》", "like": 43}, {"content": "蝎子“赖赖”[doge]", "like": 5}, {"content": "蝎子和雪球才是绝配", "like": 1}, {"content": "q是丢出一块石头，w是范围伤害，e可以限制对方攻击频率，r是带延迟的范围控制。出肉主打输出是拍地板，请问这个英雄是？", "like": 18}, {"content": "昨天疾跑点燃一级w诺克河道站撸没打过一级蝎子，望周知[呆]", "like": 31}, {"content": "主播带错了符文，符文蓝色应该带70血加伤害的，然后副系带饼干+行进速率，无论是消耗还是对拼，你都遭不住这新版的数值怪蝎子，因为这玩意Q的伤害你压根看不懂，并且你不能在它防御塔外面呆着，它卡兵线你没有权利管它，你一旦靠近，直接闪E，是直接压制住，你压根躲不开，等你被顶进防御塔了，你想跑，它还接个R，中上两路没几个能和它打的，真想打会玩的蝎子，你必须得拉扯着玩，例如剑魔，一切和蝎子贴身的，都属于白送，而且不要和它前期对拼，它被动是诺手的流血，Q是高贵的百分比最高生命值伤害。\n\n顺带说一下蝎子几个技巧，自己塔范围附近打架，闪E回推顶附近墙壁，然后接R，没有控制中空时间，无脑带人进防御塔。\n然后越塔小技巧，起QA两下，然后再E，Q有内置CD，你撞到人A出去第一下Q是第三段，A完就可以开第二个Q了，又可以打三段，打脆皮半管血就能越塔，打战士看对方英雄类型。\n还有闪E越塔，E的设定是压制，你只要闪E对方没有反应操作时间，可以直接把对面从塔下顶出去，或者顶墙上眩晕了打。\n开E时Q会一直保存着，所以不用怕E完了Q过期，E技能会被控制技能打断，越塔一些有打断技能的英雄，例如冰女，球女，诺手，劲夫一类的，需要注意点，最好使用闪E技巧。\n然后Q丢石头是有一个巨大溅射的，对方躲小兵可以直接砸小兵，伤害是一样的，同理A小兵也能溅射。\n还有，打线上时，除了越塔和贴身的情况，不要直接使用E，E启动速度很慢，很容易被当傻子，但是E到人是固定速度，很快，所以除了贴身，和想越塔，不要使用E，这样即使对方打野抓你，你可以直接E走，或者直接E对方打野，撞人带跑路。\n新版蝎子现在的强度，让我想起了曾经的上单老版本潘森，就是无脑Q你，等你血条下去，直接冲过去控住杀了，只不过蝎子更无脑了一些，因为这个E技能的存在，让对方打野还没有太好的抓它的办法。\n哪怕是带控制的打野来抓线上蝎子也不好使，例如大树，W一下蝎子，蝎子直接顶大树就走了，拉开的距离超过一个闪现的位移，而且被顶的大树是压制状态，无法使用Q打断蝎子，非常逆天。\n你就玩吧，一玩一个不吱声。", "like": 65}, {"content": "要是改成指向性丢石头，震地板减攻速，大招快速的群控是不是更强了o.O", "like": 18}, {"content": "我玩了一把就知道这玩意要带彗星和焦灼[笑哭]", "like": 66}, {"content": "提莫没有斩杀线，跑了也得死.....", "like": 0}, {"content": "今天玩了一把打，我以为w就周围一点点，这特效一看，我靠，离谱！[笑哭]", "like": 91}, {"content": "提莫没有斩杀线，跑了也得死.....", "like": 0}, {"content": "q扔石头，会拍地板，大招有范围控制，是石头人没错了", "like": 5}, {"content": "[doge]从改出来开始已经拿蝎子上单打到铂金了，哥们常年白银人[doge]", "like": 126}, {"content": "别的不说，蝎子不是大驼背了，不丑了[doge]", "like": 2}, {"content": "这w半径削一半我都不服", "like": 247}, {"content": "我记得上星期周末玩大乱斗刚好玩了章鱼妈[doge]对面蝎子为首的坦克队把我也爽到了", "like": 0}, {"content": "讲道理奥拉夫算好打蝎子的了", "like": 1}, {"content": "如果对线回血能力强的英雄怎么办", "like": 1}, {"content": "蝎子玩家真的……我觉得好多蝎子玩家这会可能觉得自己在做梦[脱单doge]", "like": 1}, {"content": "那q也很难扭，范围比一般技能大", "like": 1}, {"content": "除了那个天才，谁玩谁猛，那个天才，直接超鬼", "like": 1}, {"content": "蝎子极地更离谱，雪球中直接能把人e回去。。。[捂脸]中一个雪球比中了老蝎子的大招还难受", "like": 2}, {"content": "音速冲击[吃瓜]", "like": 1}, {"content": "他这个w的范围cd跟他这个身板不搭，你要脆皮法师有这种范围我也认，但这是个坦克啊，要么砍cd到20秒左右，要么范围最大就诺手q那样，要么身板改成亚索的，总之现在这个样绝对是不健康的。。。", "like": 0}, {"content": "蝎子目前最难打的是狼人，蝎子没有决定性的爆发杀狼人，狼人可以一直跟蝎子耗着", "like": 0}, {"content": "目前主要是蓝耗太低了，蝎子的w性能比皇子w强了不是一点，但是蓝耗太低了，导致蝎子可以无压力随便放", "like": 0}, {"content": "所以奥拉夫为什么不直接大，还一直被w减速拉扯，被控了也做不到秒解", "like": 9}, {"content": "蒙多应该好打，只有e和大的硬控，然后打不死，大招回血，一直砍，减速拉扯不了", "like": 1}, {"content": "CD太快了，范围还大，还都是aoe，而且能穿兵穿墙，赖中赖", "like": 1}, {"content": "昨天玩了一晚上中单蝎子，大概7，8盘，感觉对线很牛批，只有一把打永恩对线没打过，但我觉得是因为确实是因为对面太秀了，我确实打不过。其他对局对线期基本都可以线杀，但是打团就很难打，团战里感觉不好发挥，e技能会被各种小技能打断，大招又不好命中，抗伤害的话有感觉虚胖，没有想象那么肉，总之赢得局都赢的很吃力，甚至有一局打对面异画师，对线杀了四次，一打团我就感觉我查无此人了，存在感很低，就是挨揍。。。。。最后靠下路血C才赢的。", "like": 0}, {"content": "有点像赛尔号的纳多雷", "like": 0}, {"content": "打了这么多把上单就章鱼妈不算好打，能压能杀，过了六级以后就不好打了", "like": 0}, {"content": "《这w比我射的都远》", "like": 6}, {"content": "高抛手榴弹石头", "like": 0}, {"content": "过了对线期，这英雄巨呆", "like": 0}, {"content": "昨天我也遇到彗星蝎子了，我玩狗头把他家偷了", "like": 0}, {"content": "用酒桶对着混[吃瓜]", "like": 0}, {"content": "这b玩意没短板的吗？有肉有输出有控制还能穿墙", "like": 0}, {"content": "皇子的w和它的w比起来。。。。。。", "like": 0}, {"content": "昨天玩过，对面铁男被我打崩了，你们就玩吧，一玩一个不知声", "like": 0}, {"content": "我拿乌鸦打这个，互相坐牢呗，心之钢面具移动血瓶", "like": 0}, {"content": "这是蝎子应得的", "like": 0}, {"content": "酒桶好治这个蝎子 真的 一玩一个不吱声", "like": 0}, {"content": "狼人看来扭头就哭。什么时候加强一下狼啊", "like": 0}, {"content": "首选就放，不是就扳", "like": 0}, {"content": "好玩！来一把", "like": 0}, {"content": "老鼠武器都a的没耐久了", "like": 0}, {"content": "不可阻挡！！！不是哥们…", "like": 0}, {"content": "奥拉夫：打不过就加入，下把我也玩蝎子", "like": 0}, {"content": "这英雄现在数值机制颜值都是T0，太变态了[辣眼睛]", "like": 0}, {"content": "@添腹壹饼 @Marii丶 @塞钱斗士 @李太太请多指教 我上路的是会玩的", "like": 0}, {"content": "设计师走早了，让他改一下吸血鬼", "like": 0}, {"content": "蝎子重做了？", "like": 0}, {"content": "裸面具的鞋子才赖", "like": 0}, {"content": "一点意思没有技能设计，哪个设计师设计的？", "like": 0}, {"content": "看我秦王绕柱，蝎子🦂什么玩意[doge]", "like": 0}, {"content": "蝎子终于重做了", "like": 0}, {"content": "大乱斗的才是真变态    雪球中了直接反向e可以把人推回来    我觉得比大招还猛    而且肉的根本打不动    我一个20个头的穿甲女枪根本打不动   他还恨不得能秒我    这英雄强度完全看不懂", "like": 0}, {"content": "今天玩蝎子被万豪血虐，er万豪全能抵消了", "like": 0}, {"content": "为什么我r的时候不能w", "like": 0}, {"content": "这英雄换血不需要手法甚至不需要博弈，爽玩两天又放下了，我怕玩久了自己脑子也被它同化了。", "like": 0}, {"content": "完全不像蝎子了，像山海经里的怪物", "like": 0}, {"content": "腕豪刚上线 剑魔刚改版[笑]上单盛产怪物", "like": 0}, {"content": "怎么着也得是个三费卡", "like": 0}, {"content": "大招aoe一次拉五个[妙啊]", "like": 0}, {"content": "扔石头，拍地板，有护盾，有位移，有团控，这个英雄是？", "like": 0}, {"content": "1拖2是真爽。", "like": 0}, {"content": "而且他这个英雄恶心，就是在于你想打死他，他只要不想死，根本不可能，要是着急了，被他拖进塔里，你就没了", "like": 0}, {"content": "数值的美[无语][无语][无语]", "like": 0}, {"content": "奥恩、波比、蝎子：“我们没伤害的，很弱”[妙啊]", "like": 0}, {"content": "好像是由于蝎子弱了太久，这东西现在强一点大家也只是觉得有意思[doge]", "like": 0}, {"content": "这w百分百玩被削，甚至削机制，因为现在的w有点太强了，不是数值强，而是机制强，加护盾，范围大，还带减速？\n我觉得下一步估计就是删减速机制，再削w范围，最后逼的玩家去主q。", "like": 0}, {"content": "这就是10年冷板凳修来数值吗，妈宝龙和广州亚索的设计师，你真的该死啊，蝎子莱莱正在撕裂召唤师峡谷", "like": 1}, {"content": "既然技能范围这么远，不如。。。先攻，启动！！！", "like": 0}, {"content": "有点AD上单的感觉了[微笑]", "like": 0}, {"content": "好玩是好玩，玩了两把都是只有我一个人优势[藏狐]", "like": 0}, {"content": "赖皮蟹[傲娇]", "like": 0}, {"content": "没用，净化解不了压制", "like": 0}, {"content": "新版蝎子玩着怎么样？我看还有人哭弱啊", "like": 0}, {"content": "我们数值怪是这样的", "like": 0}, {"content": "@人类物种多样性 蝎子现在好猛，快削了", "like": 0}, {"content": "还行吧我玩狼人直接不理他[doge]", "like": 0}, {"content": "奥拉夫应该是好打蝎子的吧", "like": 0}, {"content": "其实除了最赖的w彗星以外，这个巨石q也是，跟攻击力没起来的杰斯加强炮似的，范围不小距离不短关键由于百分比所以出肉伤害也高，肉可以有高伤技能，但蝎子q这个施放条件太低了", "like": 0}, {"content": "感觉可以出个面具[doge]", "like": 0}, {"content": "水晶先锋终于不用哭泣了[doge]", "like": 0}, {"content": "打蝎子复苏+多兰盾有用没", "like": 0}, {"content": "真.蝎子莱莱", "like": 0}, {"content": "想看昨晚玩的小丑", "like": 0}, {"content": "皇子w被完爆", "like": 0}, {"content": "这玩意伤害是真高啊，数值的美", "like": 0}, {"content": "我蝎22个w秒了", "like": 0}, {"content": "剑魔天克这玩意", "like": 0}, {"content": "有道理，但是怎么打铁男[藏狐]", "like": 0}, {"content": "英雄联盟设计师对上单有一种莫名的执着，要么数值怪要么装备变态", "like": 0}, {"content": "看看石头人的e，再看看这个w[呲牙]", "like": 0}, {"content": "明明就是马克莱莱", "like": 0}, {"content": "无条件先手控制，而且这手感，太舒服了", "like": 0}, {"content": "终于有了初版的强度了", "like": 0}, {"content": "有一说一 改成这样感觉有意思多了，就是这w范围是不是有点夸张了", "like": 0}, {"content": "现在的蝎子确实好玩，能抗能打", "like": 0}, {"content": "这屌英雄强度有点夸张，线上强度高，打团随便控一堆，就是我只玩了一把不太会玩，打远程拉扯不好，但是还是挺好玩", "like": 0}, {"content": "有一说一每次感觉背景音效里那声诶很熟悉，到底是谁啊", "like": 2}, {"content": "e技能没酒桶e长，先手e能被酒桶e打断，别问我为什么知道[笑哭]", "like": 1}, {"content": "6级打八级差点被反杀，看似很赖，实则虚胖[doge]", "like": 1}, {"content": "小技巧，放W想往前放远点可以吧鼠标放在人物屁股后面，这样可以震得更加远[doge][doge][doge]", "like": 0}, {"content": "沙王的扬沙[doge]", "like": 0}, {"content": "大乱斗要是不缺前排抗伤开团的，甚至可以玩ap蝎子恶心人，比ap寒冰快乐多了[脱单doge]", "like": 0}, {"content": "但是这几能不好囤线吧，容易那兵线压过去", "like": 0}, {"content": "大招期间能w了？", "like": 0}, {"content": "@䎉銊-冷门上单", "like": 1}, {"content": "什么时候来个蟑（螳）螂恶霸", "like": 1}, {"content": "这w不就是个能穿透的吸血鬼的e么", "like": 0}, {"content": "打不了鳄鱼和诺手", "like": 0}, {"content": "奥拉夫：这w比我射的都远", "like": 0}, {"content": "啥时候出的新英雄", "like": 0}, {"content": "剩流：射的比奥拉夫远[打call][打call][打call]", "like": 0}, {"content": "奥拉夫:快点点了下把我也要玩[doge]", "like": 0}, {"content": "感觉以后w会变的跟吸血鬼的e一样，不能穿透了", "like": 1}, {"content": "这玩意能上比赛吗想看", "like": 0}, {"content": "蝎子w又称小石头人[doge]", "like": 0}, {"content": "标题暴露年龄了[妙啊]", "like": 0}, {"content": "1级q120。", "like": 0}, {"content": "蝎子现在的Q第三下a出来伤害不是比二段Q扔出来高得多吗？为啥主播Q平a前两下第三下贴身扔出去啊，这不伤害最小化了么", "like": 0}, {"content": "对线强 打团更强 一个w五个减速", "like": 0}, {"content": "新版石头人是吧", "like": 0}, {"content": "丢石头，拍地板，有护盾，大招团控，是石头人[tv_鬼脸]", "like": 0}, {"content": "这英雄玩辅助是不是也能让对面头大", "like": 0}, {"content": "这w范围多少是有点过于离谱了", "like": 0}, {"content": "Q丢东西  W有护盾 还可以造成AOE伤害  我知道了 你是拉克丝[吃瓜]", "like": 0}, {"content": "性能不是决定胜负的关键，就让我来告诉你吧", "like": 0}, {"content": "新英雄？[墨镜]", "like": 0}, {"content": "过墙，短cd护盾，不可阻挡，3段q，这不奎哥吗", "like": 0}, {"content": "必定要砍废", "like": 0}, {"content": "对线蝎子得有强续航力的英雄对线 不然消耗一点一点就被打没了", "like": 0}, {"content": "这玩意出点ap会不会更猛啊", "like": 0}, {"content": "这就是第二个广州亚索啊，又肉又有控还有伤害", "like": 0}, {"content": "弹幕说跟刚出的万豪差不多是真的假的？你均势发育哪个技能能秒满血ad", "like": 0}, {"content": "其实我觉得可以再给他优化一下。比如说在穿墙的时候可以立马抓起石头扔或者再用，穿墙技能的时候可以接大招把别人抓住，往其他地方送，撞到墙依然造成伤害和眩晕。[吃瓜]", "like": 0}, {"content": "奥拉夫的盾咋回事？技能改了吗？好久没玩了", "like": 0}, {"content": "前两天玩青钢影，对线蝎子，带了双复苏但是出门多兰剑，直接很快就被打出tp了[笑哭]后面第二天又遇到一把，这把知道多兰盾苟了", "like": 0}, {"content": "好，那么轮到我的回合了，请问度子哥，小丑怎么打蝎子莱莱[doge]", "like": 0}, {"content": "q：改为掘地，地刺\nw:改为埋沙持续伤害\ne：改为减少魔抗\nr:改为地震", "like": 0}, {"content": "我们lol也有自己的45爹[doge]", "like": 0}, {"content": "但是e很容易被打断", "like": 0}, {"content": "强度真的离谱，我一大乱斗玩家的都起兴趣单排打到黄金了", "like": 0}, {"content": "以前33个q秒人，现在是33个w了[笑哭]", "like": 0}, {"content": "你别说，带彗星有说法的", "like": 0}, {"content": "上古领主：卡尔玛x石头人x塞恩x凯隐x锤石[doge]", "like": 0}, {"content": "蝎子赖赖", "like": 0}, {"content": "转向消一下w范围消一下，OK完事", "like": 0}, {"content": "E技能，爬行形态波比[doge]", "like": 0}, {"content": "太赖了这新蝎子", "like": 0}, {"content": "玩了两把  对线只要别一套打到底  纯赖子[笑哭][笑哭][笑哭]  打谁 谁红[doge]", "like": 0}, {"content": "第一", "like": 0}, {"content": "真的赖皮，这个w不改成跟鳄鱼的一圈一样就很离谱", "like": 0}, {"content": "这w比s8的塞恩e都离谱[藏狐]", "like": 0}, {"content": "恶心吗？这设计师设计的三个英雄属于是个个是除生，除除不一样", "like": 0}, {"content": "这是新版塞恩吗[doge]", "like": 0}, {"content": "这设计师设计的什么东西", "like": 0}, {"content": "继挖掘机之后的推土机[doge]", "like": 0}, {"content": "和奎桑提刚出来那会儿一样，又肉又有输出[吃瓜]", "like": 0}, {"content": "新蝎子的Q如果近战平A三下后，石头还可以远程丢出去嘛？", "like": 0}, {"content": "1：34\n奥拉夫：这w比我射的都远[doge]", "like": 0}, {"content": "有盾有突进有控制有数值是坦克出肉有伤害还能打消耗，这不奎桑提嘛，出新皮肤了？", "like": 0}, {"content": "W氛围这么大，能不能玩AP面具啊[doge]？", "like": 0}, {"content": "700码等于对线可以偷a人。而且这盾是伤害盾，跟安妮刚改的时候一样，互换技能就等于白打你一下，换血永远不亏", "like": 0}, {"content": "吸血鬼打这个还有一点点战的感觉", "like": 0}, {"content": "这老鼠射半天盾都没打掉…不愧是奎桑提设计师设计的英雄，真是一个比一个内啥", "like": 0}, {"content": "能试试玩把ap不[doge]", "like": 0}, {"content": "今天玩日炎反甲龙龟，等级跟对面上单蝎子一样，经济也领先，单打都打不过", "like": 0}, {"content": "肚子哥，这是蝎子W削弱后玩的吗，是的话我也练练[doge][doge]", "like": 0}, {"content": "这玩意只能带彗星[笑哭]", "like": 0}, {"content": "就是主播的玩法，被我用奥恩打出💩来了", "like": 0}, {"content": "刚刚好", "like": 0}, {"content": "太美丽了这数值[脱单doge]", "like": 0}, {"content": "谁能想到，一个出场率垫底的玩意重做能正面打奥拉夫[笑哭]只能说这设计师好似", "like": 0}, {"content": "W范围太大加减速有点太恶心", "like": 0}, {"content": "这拉夫也太菜了", "like": 0}, {"content": "只会扔长斧头的拉夫是这样的", "like": 0}, {"content": "可以，对起线来巨恶心", "like": 0}, {"content": "女神泪出门q和w消耗是真恶心", "like": 0}, {"content": "讲实话这拉夫太怂了，那有拉夫这么怂的", "like": 0}, {"content": "[doge]好恶心啊", "like": 0}, {"content": "远古小丑[doge]", "like": 0}, {"content": "掘地小丑！", "like": 0}, {"content": "第一[doge]", "like": 1}, {"content": "觅渡小屋", "like": 5}, {"content": "肚子哥", "like": 0}, {"content": "我卡了，哈哈哈，变成第一个肚子哥的视频了[嗑瓜子][嗑瓜子][嗑瓜子]", "like": 0}, {"content": "今天打个瓦 家里开局就挂机一个 然后队友说了句 觅渡大战乐言 我：O.o？", "like": 0}]}